pdfmark/VERSION.txt
pdfmark/__init__.py
pdfmark/__main__.py
pdfmark-0.2.0.dist-info/DESCRIPTION.rst
pdfmark-0.2.0.dist-info/LICENSE.txt
pdfmark-0.2.0.dist-info/METADATA
pdfmark-0.2.0.dist-info/RECORD
pdfmark-0.2.0.dist-info/WHEEL
pdfmark-0.2.0.dist-info/entry_points.txt
pdfmark-0.2.0.dist-info/metadata.json
pdfmark-0.2.0.dist-info/top_level.txt
