Metadata-Version: 2.0
Name: pdfmark
Version: 0.2.0
Summary: PDF Bookmark Adder
Home-page: https://gitlab.com/imtheforce/pdfmark
Author: Gu Zhengxiong
Author-email: rectigu@gmail.com
License: GPL-3
Keywords: PDF Documents,Automatically Add Bookmarks,Regex
Platform: UNKNOWN
Requires-Dist: pycliprog (==0.3.0)
Requires-Dist: pypdf2
